CHANGES
MANIFEST.in
README.rst
setup.py
src/slimit/__init__.py
src/slimit/ast.py
src/slimit/lexer.py
src/slimit/lextab.py
src/slimit/mangler.py
src/slimit/minifier.py
src/slimit/parser.py
src/slimit/scope.py
src/slimit/unicode.py
src/slimit/yacctab.py
src/slimit.egg-info/PKG-INFO
src/slimit.egg-info/SOURCES.txt
src/slimit.egg-info/dependency_links.txt
src/slimit.egg-info/entry_points.txt
src/slimit.egg-info/not-zip-safe
src/slimit.egg-info/requires.txt
src/slimit.egg-info/top_level.txt
src/slimit/tests/__init__.py
src/slimit/tests/test_cmd.py
src/slimit/tests/test_ecmavisitor.py
src/slimit/tests/test_lexer.py
src/slimit/tests/test_mangler.py
src/slimit/tests/test_minifier.py
src/slimit/tests/test_nodevisitor.py
src/slimit/tests/test_parser.py
src/slimit/visitors/__init__.py
src/slimit/visitors/ecmavisitor.py
src/slimit/visitors/minvisitor.py
src/slimit/visitors/nodevisitor.py
src/slimit/visitors/scopevisitor.py