Metadata-Version: 1.0
Name: slimit
Version: 0.6
Summary: SlimIt - JavaScript minifier
Home-page: http://slimit.org
Author: Ruslan Spivak
Author-email: ruslan.spivak@gmail.com
License: MIT
Platform: UNKNOWN
Classifier: Intended Audience :: Developers
Classifier: License :: OSI Approved :: MIT License
Classifier: Programming Language :: Python
Classifier: Topic :: Software Development :: Compilers
Classifier: Operating System :: Unix
